towhee/__init__.py
towhee/__main__.py
towhee/data_loader.py
towhee/command/__init__.py
towhee/command/cmdline.py
towhee/command/develop.py
towhee/command/execute.py
towhee/command/repo.py
towhee/command/user.py
towhee/data/__init__.py
towhee/data/dataset/__init__.py
towhee/data/dataset/dataset.py
towhee/data/dataset/image_datasets.py
towhee/datacollection/__init__.py
towhee/datacollection/data_collection.py
towhee/datacollection/entity.py
towhee/datacollection/mixins/__init__.py
towhee/datacollection/mixins/display.py
towhee/hub/__init__.py
towhee/hub/cache_manager.py
towhee/hub/downloader.py
towhee/hub/operator_manager.py
towhee/hub/pipeline_manager.py
towhee/hub/repo_manager.py
towhee/operator/__init__.py
towhee/operator/base.py
towhee/operator/nop.py
towhee/pipelines/__init__.py
towhee/pipelines/_builtin_pipeline.py
towhee/pipelines/insert_milvus.py
towhee/pipelines/search_milvus.py
towhee/pipelines/sentence_embedding.py
towhee/pipelines/text_image_embedding.py
towhee/pipelines/video_copy_detection.py
towhee/pipelines/video_embedding.py
towhee/runtime/__init__.py
towhee/runtime/auto_config.py
towhee/runtime/auto_pipes.py
towhee/runtime/check_utils.py
towhee/runtime/constants.py
towhee/runtime/dag_repr.py
towhee/runtime/data_queue.py
towhee/runtime/factory.py
towhee/runtime/node_config.py
towhee/runtime/node_repr.py
towhee/runtime/pipeline.py
towhee/runtime/pipeline_loader.py
towhee/runtime/runtime_conf.py
towhee/runtime/runtime_pipeline.py
towhee/runtime/schema_repr.py
towhee/runtime/time_profiler.py
towhee/runtime/nodes/__init__.py
towhee/runtime/nodes/_concat.py
towhee/runtime/nodes/_filter.py
towhee/runtime/nodes/_flat_map.py
towhee/runtime/nodes/_map.py
towhee/runtime/nodes/_output.py
towhee/runtime/nodes/_reduce.py
towhee/runtime/nodes/_single_input.py
towhee/runtime/nodes/_time_window.py
towhee/runtime/nodes/_window.py
towhee/runtime/nodes/_window_all.py
towhee/runtime/nodes/_window_base.py
towhee/runtime/nodes/node.py
towhee-1.1.3.dist-info/LICENSE
towhee-1.1.3.dist-info/METADATA
towhee-1.1.3.dist-info/WHEEL
towhee-1.1.3.dist-info/entry_points.txt
towhee-1.1.3.dist-info/top_level.txt
towhee-1.1.3.dist-info/RECORD
