Metadata-Version: 2.1
Name: towhee
Version: 1.1.3
Summary: Towhee is a framework that helps you encode your unstructured data into embeddings.
Home-page: https://github.com/towhee-io/towhee
Author: Towhee Team
Author-email: towhee-team@zilliz.com
License: http://www.apache.org/licenses/LICENSE-2.0
Platform: unix
Platform: linux
Platform: osx
Platform: win32
License-File: LICENSE
Requires-Dist: requests >=2.12.5
Requires-Dist: tqdm >=4.59.0
Requires-Dist: tabulate
Requires-Dist: numpy
Requires-Dist: twine
Requires-Dist: tenacity
Requires-Dist: pydantic
Requires-Dist: contextvars ; python_version <= "3.6"
Requires-Dist: importlib-resources ; python_version<'3.7'
